penchmark/__init__.py
penchmark/_core.py
penchmark/_defs.py
penchmark/_helpers.py
penchmark/_report.py
penchmark/charts.py
penchmark/tests/__init__.py
penchmark/tests/test_benchmark.py
penchmark/tests/test_name_generator.py
penchmark-0.1.0.dist-info/LICENSE.txt
penchmark-0.1.0.dist-info/METADATA
penchmark-0.1.0.dist-info/WHEEL
penchmark-0.1.0.dist-info/top_level.txt
penchmark-0.1.0.dist-info/RECORD
