Metadata-Version: 2.1
Name: penchmark
Version: 0.1.0
Summary: Python code benchmark library
Home-page: https://github.com/ruzzz/penchmark
Author: Ruslan Zaporojets
Author-email: ruzzzua@gmail.com
License: UNKNOWN
Keywords: benchmark
Platform: UNKNOWN
Classifier: License :: OSI Approved :: MIT License
Classifier: Operating System :: OS Independent
Classifier: Programming Language :: Python :: 3.6
Classifier: Programming Language :: Python :: 3.7
Classifier: Programming Language :: Python :: 3.8
Classifier: Topic :: Software Development :: Testing
Classifier: Topic :: System :: Benchmark
Classifier: Topic :: Utilities
Requires-Python: >=3.6
Requires-Dist: tabulate (>=0.8.7)
Provides-Extra: charts
Requires-Dist: matplotlib (>=3.2.2) ; extra == 'charts'
Requires-Dist: pandas (>=1.0.5) ; extra == 'charts'
Requires-Dist: seaborn (>=0.10.1) ; extra == 'charts'
Provides-Extra: dev
Requires-Dist: mypy (>=0.782) ; extra == 'dev'
Requires-Dist: pylint (>=2.5.3) ; extra == 'dev'
Requires-Dist: pylint-quotes (>=0.2.1) ; extra == 'dev'
Requires-Dist: pytest (>=5.4.3) ; extra == 'dev'
Requires-Dist: pytest-cov (>=2.10.0) ; extra == 'dev'
